LICENSE
README.md
setup.py
lovetiklib/__init__.py
lovetiklib.egg-info/PKG-INFO
lovetiklib.egg-info/SOURCES.txt
lovetiklib.egg-info/dependency_links.txt
lovetiklib.egg-info/requires.txt
lovetiklib.egg-info/top_level.txt