Metadata-Version: 2.1
Name: lovetiklib
Version: 0.0.1
Summary: With This Package Can You Download Any TikTok Video from lovetik.com
Home-page: https://github.com/muamelAmeer/lovetik-lib
Author: Muamel Ameer
Author-email: amowallet@gmail.com
Project-URL: Source, https://github.com/muamelAmeer/lovetik-lib
Project-URL: Dev Lib, https://github.com/muamelAmeer
Project-URL: Documentation, https://github.com/muamelAmeer/lovetik-lib
Keywords: tiktok
Classifier: Development Status :: 1 - Planning
Classifier: Intended Audience :: Developers
Classifier: Programming Language :: Python :: 3
Classifier: Operating System :: Unix
Classifier: Operating System :: MacOS :: MacOS X
Classifier: Operating System :: Microsoft :: Windows
License-File: LICENSE
